thrift2pyi/__init__.py
thrift2pyi/__main__.py
thrift2pyi/__version__.py
thrift2pyi/convert.py
thrift2pyi/exceptions.py
thrift2pyi/main.py
thrift2pyi/peg.py
thrift2pyi-1.0.5.dist-info/LICENSE
thrift2pyi-1.0.5.dist-info/METADATA
thrift2pyi-1.0.5.dist-info/WHEEL
thrift2pyi-1.0.5.dist-info/entry_points.txt
thrift2pyi-1.0.5.dist-info/top_level.txt
thrift2pyi-1.0.5.dist-info/RECORD
