Metadata-Version: 2.1
Name: thrift2pyi
Version: 1.0.5
Summary: convert thrift to pyi
Author: yanweizhi
Author-email: yanweizhi <yanweizhi@bytedance.com>
Project-URL: Homepage, https://github.com/pypa/sampleproject
Project-URL: Bug Tracker, https://github.com/pypa/sampleproject/issues
Keywords: thrift2pyi
Classifier: Intended Audience :: Developers
Classifier: Programming Language :: Python :: 2
Classifier: Programming Language :: Python :: 2.7
Classifier: Programming Language :: Python :: 3
Classifier: Programming Language :: Python :: 3.4
Requires-Python: >=2.7,!=3.0.*,!=3.1.*,!=3.2.*,!=3.3.*
License-File: LICENSE
Requires-Dist: six (<2.0.0,>=1.11.0)
Requires-Dist: pypeg2 (<3.0.0,>=2.15.2)
Requires-Dist: thriftpy2 (<1.0.0,>=0.4.2)
Requires-Dist: yapf (<1.0.0,>=0.22.0)
Requires-Dist: typing (>=3.6.4) ; python_version<"3.5"
Provides-Extra: dev
Requires-Dist: flake8 (<4.0.0,>=3.5.0) ; extra == 'dev'
Requires-Dist: nose (<2.0.0,>=1.3.7) ; extra == 'dev'
Requires-Dist: tox (<4.0.0,>=3.0.0) ; extra == 'dev'
Requires-Dist: mypy (>=0.620) ; (python_version >= "3.4") and extra == 'dev'
